di_compression/__init__.py
di_compression/deflate.py
di_compression/huffman.py
di_compression/lz77.py
di_compression/lz78.py
di_compression/lzw.py
di_compression-0.1.1.dist-info/METADATA
di_compression-0.1.1.dist-info/WHEEL
di_compression-0.1.1.dist-info/top_level.txt
di_compression-0.1.1.dist-info/RECORD
